{"name":"Месианский Разделитель","description":"Изначально созданная оружейниками Месии для расчленения неумирающих мутантов, что бродят по ночной стороне их мира, эта тяжелая винтовка с вращающимся блоком из 4-х стволов выстреливает широкий плоский луч с настраиваемым углом наклона. Если непоглощенный урон этого оружия в конечность больше T.b цели, он также отрезает эту конечность, прижигая культю. ","weaponClass":"Ручное","rof":"О/-/-","damage":"1к10+5Э","reload":"Полн","properties":"Разящее(2),Надёжное","rarity":"0","typeEquipment":"Range","range":100,"penetration":0,"clip":12,"amount":1,"weight":5.0}
