{"name":"Рапира Велькир","description":"Эта зачарованная рапира изгибается и извивается, поражая врагов даже сквозь лучшую защитную технику, и многие дуэлянты готовы продать душу, чтобы заполучить ее себе. Иронично, эта рапира действительно с каждым выпадом вытягивает крупицу души владельца, чтобы питать свои зачарования. Каждый раз, когда она убивает разумное существо, персонаж должен пройти тест на W+0, или получить 1 Усталости. ","properties":"Гибкое,Укрепленное,Бритвенно-острое","type":"","weaponClass":"Рукопашное","damage":"1к10+8Р","rarity":"5","typeEquipment":"Melee","penetration":8,"amount":1,"weight":1.0}
